fieldviz_mini/__init__.py
fieldviz_mini/fields.py
fieldviz_mini/integrators.py
fieldviz_mini/presets.py
fieldviz_mini/visualize.py
fieldviz_mini-0.1.0.dist-info/licenses/LICENSE
fieldviz_mini-0.1.0.dist-info/METADATA
fieldviz_mini-0.1.0.dist-info/WHEEL
fieldviz_mini-0.1.0.dist-info/top_level.txt
fieldviz_mini-0.1.0.dist-info/RECORD
