Metadata-Version: 2.4
Name: fieldviz-mini
Version: 0.1.0
Summary: Tiny vector-field and attractor visualizer
Author-email: RJ Sabouhi <rjsabouhi@gmail.com>
License: MIT License
Project-URL: Homepage, https://github.com/rjsabouhi/fieldviz-mini
Keywords: dynamics,vector fields,visualization,attractors,complex systems
Requires-Python: >=3.9
License-File: LICENSE
Requires-Dist: numpy
Requires-Dist: matplotlib
Requires-Dist: pytest>=8.4.2
Dynamic: license-file
